dynafed_storagestats/__init__.py
dynafed_storagestats/args.py
dynafed_storagestats/base.py
dynafed_storagestats/configloader.py
dynafed_storagestats/exceptions.py
dynafed_storagestats/helpers.py
dynafed_storagestats/json.py
dynafed_storagestats/logger.py
dynafed_storagestats/memcache.py
dynafed_storagestats/output.py
dynafed_storagestats/reports.py
dynafed_storagestats/runner.py
dynafed_storagestats/time.py
dynafed_storagestats/version.py
dynafed_storagestats/xml.py
dynafed_storagestats/azure/__init__.py
dynafed_storagestats/azure/base.py
dynafed_storagestats/azure/helpers.py
dynafed_storagestats/dav/__init__.py
dynafed_storagestats/dav/base.py
dynafed_storagestats/dav/helpers.py
dynafed_storagestats/s3/__init__.py
dynafed_storagestats/s3/base.py
dynafed_storagestats/s3/helpers.py
dynafed_storagestats-1.0.40.dist-info/LICENSE
dynafed_storagestats-1.0.40.dist-info/METADATA
dynafed_storagestats-1.0.40.dist-info/WHEEL
dynafed_storagestats-1.0.40.dist-info/entry_points.txt
dynafed_storagestats-1.0.40.dist-info/top_level.txt
dynafed_storagestats-1.0.40.dist-info/RECORD
