Metadata-Version: 2.1
Name: dynafed-storagestats
Version: 1.0.40
Summary: Dynafed Storage Stats Module
Home-page: https://github.com/hep-gc/dynafed_storagestats
Author: Fernando Fernandez Galindo
Author-email: ffernandezgalindo@triumf.ca
License: Apache
Platform: UNKNOWN
Classifier: Development Status :: 4 - Beta
Classifier: License :: OSI Approved :: Apache Software License
Classifier: Programming Language :: Python :: 3
Requires-Python: ~=3.4
Requires-Dist: azure-storage (==0.36.0)
Requires-Dist: boto3
Requires-Dist: lxml
Requires-Dist: prometheus-client
Requires-Dist: python-memcached
Requires-Dist: PyYAML
Requires-Dist: requests
Requires-Dist: requests-aws4auth
